pdf_to_md_llm/__init__.py
pdf_to_md_llm/__main__.py
pdf_to_md_llm/cli.py
pdf_to_md_llm/converter.py
pdf_to_md_llm/providers.py
pdf_to_md_llm-2.7.1.dist-info/METADATA
pdf_to_md_llm-2.7.1.dist-info/WHEEL
pdf_to_md_llm-2.7.1.dist-info/entry_points.txt
pdf_to_md_llm-2.7.1.dist-info/licenses/LICENSE
pdf_to_md_llm-2.7.1.dist-info/RECORD
