Metadata-Version: 2.4
Name: pdf-to-md-llm
Version: 2.7.1
Summary: Library and CLI to convert PDF documents to clean, well-structured Markdown using LLM-assisted processing, leveraging Antrhopic and OpenAI models for intelligent extraction of text, tables, and complex layouts.
Project-URL: Homepage, https://github.com/densom/pdf-to-md-llm
Project-URL: Repository, https://github.com/densom/pdf-to-md-llm
Project-URL: Issues, https://github.com/densom/pdf-to-md-llm/issues
Project-URL: Funding, https://buymeacoffee.com/densom
Author-email: Dennis Somerville <densom@users.noreply.github.com>
License: MIT
License-File: LICENSE
Keywords: ai,anthropic,converter,llm,markdown,openai,pdf
Classifier: Development Status :: 4 - Beta
Classifier: Intended Audience :: Developers
Classifier: License :: OSI Approved :: MIT License
Classifier: Programming Language :: Python :: 3
Classifier: Programming Language :: Python :: 3.10
Classifier: Programming Language :: Python :: 3.11
Classifier: Programming Language :: Python :: 3.12
Classifier: Programming Language :: Python :: 3.13
Classifier: Topic :: Software Development :: Libraries :: Python Modules
Classifier: Topic :: Text Processing :: Markup :: Markdown
Requires-Python: >=3.10
Requires-Dist: anthropic>=0.46.0
Requires-Dist: click>=8.3.0
Requires-Dist: openai>=1.0.0
Requires-Dist: pymupdf>=1.26.4
Requires-Dist: python-dotenv>=1.1.1
